nnabla_browser/__init__.py
nnabla_browser/directory_monitoring.py
nnabla_browser/parse_nnabla_function.py
nnabla_browser/server.py
nnabla_browser/server_sent_event.py
nnabla_browser/utils.py
nnabla_browser/dist/index.html
nnabla_browser/dist/static/css/index.7fb2412f.css
nnabla_browser/dist/static/js/chunk-vendors.8046adae.js
nnabla_browser/dist/static/js/chunk-vendors.8046adae.js.map
nnabla_browser/dist/static/js/index.a01fa795.js
nnabla_browser/dist/static/js/index.a01fa795.js.map
nnabla_browser-0.2.0.dist-info/LICENSE
nnabla_browser-0.2.0.dist-info/METADATA
nnabla_browser-0.2.0.dist-info/WHEEL
nnabla_browser-0.2.0.dist-info/entry_points.txt
nnabla_browser-0.2.0.dist-info/top_level.txt
nnabla_browser-0.2.0.dist-info/RECORD
